mcp_server_everything_wrong/__init__.py
mcp_server_everything_wrong/__main__.py
mcp_server_everything_wrong/server.py
mcp_server_everything_wrong-0.2.1.dist-info/METADATA
mcp_server_everything_wrong-0.2.1.dist-info/WHEEL
mcp_server_everything_wrong-0.2.1.dist-info/entry_points.txt
mcp_server_everything_wrong-0.2.1.dist-info/licenses/LICENSE.md
mcp_server_everything_wrong-0.2.1.dist-info/RECORD
