Metadata-Version: 2.4
Name: mcp-server-everything-wrong
Version: 0.2.1
Summary: Show case common MCP server security concerns
License-File: LICENSE.md
Requires-Python: >=3.10
Requires-Dist: httpx
Requires-Dist: mcp[server]>=1.9.0
Requires-Dist: pydantic
